hexea/__init__.py
hexea/_board.cpython-311-darwin.so
hexea/board.cpp
hexea-0.3.0.dist-info/LICENSE.txt
hexea-0.3.0.dist-info/METADATA
hexea-0.3.0.dist-info/WHEEL
hexea-0.3.0.dist-info/top_level.txt
hexea-0.3.0.dist-info/RECORD
