Metadata-Version: 2.1
Name: hexea
Version: 0.3.0
Summary: Python library for the games of Hex and Y
Author-email: Chip Hollingsworth <cholling@gmail.com>
License: Copyright (c) 2021 Charles Hollingsworth <cholling@gmail.com>
Project-URL: repository, https://codeberg.org/cholling/hexea
Classifier: License :: OSI Approved :: MIT License
Classifier: Programming Language :: Python
Classifier: Programming Language :: Python :: 3
Requires-Python: <4.0,>=3.11
License-File: LICENSE.txt
Provides-Extra: dev
Requires-Dist: pytest ; extra == 'dev'
Requires-Dist: black ; extra == 'dev'
Requires-Dist: pylint ; extra == 'dev'
Requires-Dist: pyright ; extra == 'dev'
Requires-Dist: sphinx ; extra == 'dev'
